bot_auth/__init__.py
bot_auth-0.3.1.dist-info/WHEEL
bot_auth-0.3.1.dist-info/METADATA
bot_auth-0.3.1.dist-info/RECORD
