Metadata-Version: 2.3
Name: bot-auth
Version: 0.3.1
Summary: A library to check for AI Bot Authentication using the latest HTTP header Signature.
Author: Atish Joottun, Thibault Meunier, Antonin Vlcek
Author-email: Atish Joottun <atish.joottun@cyberstorm.mu>, Thibault Meunier <mail@thibaultmeunier.com>, Antonin Vlcek <tony@vlcek.dev>
License:                                  Apache License
Requires-Dist: cryptography>=45.0.0
Requires-Dist: http-message-signatures>=0.7.0
Requires-Dist: requests>=2.25.0
Requires-Python: >=3.11
